LICENSE
p115pickcode/__init__.py
p115pickcode/py.typed
p115pickcode-0.0.5.3.dist-info/LICENSE
p115pickcode-0.0.5.3.dist-info/LICENSE_zh
p115pickcode-0.0.5.3.dist-info/METADATA
p115pickcode-0.0.5.3.dist-info/WHEEL
p115pickcode-0.0.5.3.dist-info/RECORD
